rc3/__init__.py
rc3/__main__.py
rc3/assets/theme.tcss
rc3/core/__init__.py
rc3/core/app.py
rc3/core/command_runner.py
rc3/core/config_manager.py
rc3/core/plugin_manager.py
rc3/plugins/__init__.py
rc3/plugins/base.py
rc3/plugins/command_reference.py
rc3/plugins/dev_tools.py
rc3/plugins/file_browser.py
rc3/plugins/navigator.py
rc3/plugins/quick_commands.py
rc3/plugins/system_info.py
rc3/plugins/working_directory.py
rc3_tui-0.4.7.dist-info/licenses/LICENSE
rc3_tui-0.4.7.dist-info/METADATA
rc3_tui-0.4.7.dist-info/WHEEL
rc3_tui-0.4.7.dist-info/entry_points.txt
rc3_tui-0.4.7.dist-info/top_level.txt
rc3_tui-0.4.7.dist-info/RECORD
