Metadata-Version: 2.4
Name: rc3-tui
Version: 0.4.7
Summary: RC3 Command Center - Modular CLI Dashboard with Keyboard-Driven Command Execution
Author: RC3
License: MIT
Project-URL: Homepage, https://github.com/Rcarraway3/sandbox
Project-URL: Repository, https://github.com/Rcarraway3/sandbox
Project-URL: Issues, https://github.com/Rcarraway3/sandbox/issues
Keywords: cli,tui,dashboard,terminal,textual,command-center
Classifier: Development Status :: 4 - Beta
Classifier: Environment :: Console
Classifier: Intended Audience :: Developers
Classifier: License :: OSI Approved :: MIT License
Classifier: Operating System :: OS Independent
Classifier: Programming Language :: Python :: 3
Classifier: Programming Language :: Python :: 3.10
Classifier: Programming Language :: Python :: 3.11
Classifier: Programming Language :: Python :: 3.12
Classifier: Topic :: Software Development :: User Interfaces
Classifier: Topic :: System :: Monitoring
Classifier: Topic :: Utilities
Requires-Python: >=3.10
License-File: LICENSE
Requires-Dist: textual>=0.52.0
Requires-Dist: pyyaml>=6.0
Requires-Dist: rich>=13.7.0
Requires-Dist: psutil>=5.9.0
Provides-Extra: dev
Requires-Dist: textual-dev>=1.0.0; extra == "dev"
Dynamic: license-file
